npc_shields/__init__.py
npc_shields/injections.py
npc_shields/insertions.py
npc_shields/py.typed
npc_shields/shields.py
npc_shields/types.py
npc_shields/widgets.py
npc_shields/drawings/2001.svg
npc_shields/drawings/2002.svg
npc_shields/drawings/2005.svg
npc_shields/drawings/2006.svg
npc_shields/drawings/2011.svg
npc_shields/drawings/2014.svg
npc_shields/drawings/Templeton_combos.svg
npc_shields/hole_coordinates/2001.csv
npc_shields/hole_coordinates/2002.csv
npc_shields/hole_coordinates/2005.csv
npc_shields/hole_coordinates/2006.csv
npc_shields/hole_coordinates/2011.csv
npc_shields/hole_coordinates/2014.csv
npc_shields-0.1.14.dist-info/METADATA
npc_shields-0.1.14.dist-info/WHEEL
npc_shields-0.1.14.dist-info/top_level.txt
npc_shields-0.1.14.dist-info/RECORD
