Metadata-Version: 2.2
Name: npc_shields
Version: 0.1.14
Summary: Tools for Neuropixels probe insertion: providing suggested targets, recording actual insertions, storing notes.
Author-email: bjhardcastle <ben.hardcastle@alleninstitute.org>
License: MIT
Project-URL: Repository, https://github.com/AllenInstitute/npc_shields
Project-URL: Issues, https://github.com/AllenInstitute/npc_shields/issues
Classifier: Programming Language :: Python :: 3
Classifier: Programming Language :: Python :: 3.9
Classifier: Programming Language :: Python :: 3.10
Classifier: Programming Language :: Python :: 3.11
Classifier: License :: OSI Approved :: MIT License
Classifier: Operating System :: Microsoft :: Windows
Classifier: Operating System :: POSIX :: Linux
Requires-Python: >=3.9
Requires-Dist: ipywidgets>=7
Requires-Dist: npc-session>=0.1.30
Requires-Dist: pydantic>=2.7.1
Requires-Dist: eval-type-backport>=0.2.0
